fractal_projections/__init__.py
fractal_projections/examples.py
fractal_projections/py.typed
fractal_projections/builders/__init__.py
fractal_projections/builders/base.py
fractal_projections/builders/django.py
fractal_projections/builders/duckdb.py
fractal_projections/builders/elasticsearch.py
fractal_projections/builders/firestore.py
fractal_projections/builders/mongo.py
fractal_projections/builders/postgres.py
fractal_projections/mixins/__init__.py
fractal_projections/mixins/base.py
fractal_projections/mixins/django.py
fractal_projections/mixins/duckdb.py
fractal_projections/mixins/firestore.py
fractal_projections/mixins/mongo.py
fractal_projections/mixins/postgres.py
fractal_projections/projections/__init__.py
fractal_projections/projections/fields.py
fractal_projections/projections/grouping.py
fractal_projections/projections/limiting.py
fractal_projections/projections/ordering.py
fractal_projections/projections/query.py
fractal_projections-0.3.1.dist-info/licenses/LICENSE
fractal_projections-0.3.1.dist-info/WHEEL
fractal_projections-0.3.1.dist-info/METADATA
fractal_projections-0.3.1.dist-info/RECORD
